[{"pageid":1616,"ns":0,"title":"Drive"},{"pageid":1639,"ns":0,"title":"Absence"},{"pageid":1682,"ns":0,"title":"Specular image"},{"pageid":1706,"ns":0,"title":"Part-Object","redirect":""},{"pageid":3782,"ns":0,"title":"Part-object","redirect":""},{"pageid":3917,"ns":0,"title":"Index:Parallax View"},{"pageid":4768,"ns":0,"title":"Lost object"},{"pageid":5098,"ns":0,"title":"Part object","redirect":""},{"pageid":5099,"ns":0,"title":"Part Object","redirect":""},{"pageid":5100,"ns":0,"title":"Partial Object","redirect":""},{"pageid":5101,"ns":0,"title":"Partial-Object","redirect":""},{"pageid":5102,"ns":0,"title":"Partial-object","redirect":""},{"pageid":5237,"ns":0,"title":"Objet partiel","redirect":""},{"pageid":5413,"ns":0,"title":"Working"},{"pageid":6076,"ns":0,"title":"Objet (petit) a"}]